alicebot_plugin_template-0.1.10.dist-info/METADATA
alicebot_plugin_template-0.1.10.dist-info/WHEEL
alicebot_plugin_template-0.1.10.dist-info/licenses/LICENSE
alicebot_plugin_template/__init__.py
alicebot_plugin_template/config.py
alicebot_plugin_template-0.1.10.dist-info/RECORD
