Metadata-Version: 2.1
Name: alicebot-plugin-template
Version: 0.1.10
Summary: AliceBot Plugin Template.
Keywords: bot,chatbot,alicebot,tag1,tag2
Author-Email: AliceBot <concontact@alicebot.dev>
License: MIT
Classifier: Development Status :: 3 - Alpha
Classifier: Framework :: AsyncIO
Classifier: Framework :: Robot Framework
Classifier: Framework :: Robot Framework :: Library
Classifier: License :: OSI Approved :: MIT License
Classifier: Operating System :: OS Independent
Classifier: Programming Language :: Python :: 3
Classifier: Topic :: Communications :: Chat
Project-URL: Homepage, https://docs.alicebot.dev/
Project-URL: Documentation, https://docs.alicebot.dev/
Project-URL: Repository, https://github.com/AliceBotProject/alicebot-plugin-template
Project-URL: Changelog, https://docs.alicebot.dev/changelog.html
Requires-Python: >=3.8
Requires-Dist: alicebot>=0.10.0
